README.rst
setup.cfg
setup.py
evaluator/__init__.py
evaluator/evaluator.py
evaluator/hand.py
evaluator/main.py
hand_evaluator.egg-info/PKG-INFO
hand_evaluator.egg-info/SOURCES.txt
hand_evaluator.egg-info/dependency_links.txt
hand_evaluator.egg-info/entry_points.txt
hand_evaluator.egg-info/namespace_packages.txt
hand_evaluator.egg-info/requires.txt
hand_evaluator.egg-info/top_level.txt