Metadata-Version: 1.1
Name: hand-evaluator
Version: 0.0.1a
Summary: hand_evaluator
Home-page: git.darkhorse.com/jbeedy/hand_evaluator
Author: jamesbeedy
Author-email: jamesbeedy@gmail.com
License: UNKNOWN
Download-URL: https://github.com/jamesbeedy/hand_evaluator
Keywords: sample setuptools development
Platform: Any
Classifier: Development Status :: 3 - Alpha
Classifier: Intended Audience :: Developers
Classifier: Topic :: Software Development :: Build Tools
Classifier: License :: OSI Approved :: Apache Software License
Classifier: Programming Language :: Python
Classifier: Programming Language :: Python :: 2
Classifier: Programming Language :: Python :: 2.7
Classifier: Programming Language :: Python :: 3
Classifier: Programming Language :: Python :: 3.2
Classifier: Intended Audience :: Developers
Classifier: Environment :: Console
